text_spider/PrintIt.py
text_spider/__init__.py
text_spider/parse.py
text_spider/spider.py
text_spider-1.0.2.data/scripts/text-spider
text_spider-1.0.2.dist-info/DESCRIPTION.rst
text_spider-1.0.2.dist-info/METADATA
text_spider-1.0.2.dist-info/RECORD
text_spider-1.0.2.dist-info/WHEEL
text_spider-1.0.2.dist-info/metadata.json
text_spider-1.0.2.dist-info/top_level.txt
